cron_machine/__init__.py
cron_machine/cron_machine.py
cron_machine-0.1.0.dist-info/LICENSE
cron_machine-0.1.0.dist-info/METADATA
cron_machine-0.1.0.dist-info/WHEEL
cron_machine-0.1.0.dist-info/RECORD
