Metadata-Version: 2.3
Name: cron-machine
Version: 0.1.0
Summary: Python module with cron runner
License: MIT
Author: Kirill Sulim
Author-email: kirillsulim@gmail.com
Requires-Python: >=3.10,<4.0
Classifier: License :: OSI Approved :: MIT License
Classifier: Programming Language :: Python :: 3
Classifier: Programming Language :: Python :: 3.10
Classifier: Programming Language :: Python :: 3.11
Classifier: Programming Language :: Python :: 3.12
Classifier: Programming Language :: Python :: 3.13
Requires-Dist: croniter (>=6.0.0,<7.0.0)
Requires-Dist: pytz (>=2025.1,<2026.0)
